{
  "category": "Abstract",
  "name": "Twilight",
  "color_count": 8,
  "colors": [
    {
      "r": 3,
      "g": 4,
      "b": 17,
      "percentage": 20.68242260023082
    },
    {
      "r": 71,
      "g": 57,
      "b": 69,
      "percentage": 11.475738872999147
    },
    {
      "r": 184,
      "g": 32,
      "b": 137,
      "percentage": 4.119624667569873
    },
    {
      "r": 11,
      "g": 90,
      "b": 171,
      "percentage": 15.897435897435896
    },
    {
      "r": 142,
      "g": 98,
      "b": 85,
      "percentage": 9.380300065231573
    },
    {
      "r": 182,
      "g": 163,
      "b": 73,
      "percentage": 14.31180691454664
    },
    {
      "r": 226,
      "g": 217,
      "b": 214,
      "percentage": 8.200110391891213
    },
    {
      "r": 236,
      "g": 232,
      "b": 117,
      "percentage": 15.932560590094837
    }
  ]
}